biiopython/__init__.py
biiopython/lab1.py
biiopython/lab10.py
biiopython/lab2.py
biiopython/lab3.py
biiopython/lab4.py
biiopython/lab5.py
biiopython/lab6.py
biiopython/lab7.py
biiopython/lab8.py
biiopython/lab9.py
biiopython/pdb1a3n.ent
biiopython/data/aligned_sequences.aln
biiopython/data/aligned_sequences.fasta
biiopython/data/example_output.gb
biiopython/data/fasta_1.fasta
biiopython/data/genbank_1.gb
biiopython/data/muscle3.8.31_i86win32.exe
biiopython/data/phylogenetic_tree.nwk
biiopython-0.0.5.dist-info/licenses/LICENSE
biiopython-0.0.5.dist-info/METADATA
biiopython-0.0.5.dist-info/WHEEL
biiopython-0.0.5.dist-info/top_level.txt
biiopython-0.0.5.dist-info/RECORD
